terasim_nde_nade/__init__.py
terasim_nde_nade/adversity/__init__.py
terasim_nde_nade/adversity/static/__init__.py
terasim_nde_nade/adversity/static/collision.py
terasim_nde_nade/adversity/static/construction.py
terasim_nde_nade/adversity/static/stalled_object.py
terasim_nde_nade/adversity/vehicles/__init__.py
terasim_nde_nade/adversity/vehicles/follower_adversity.py
terasim_nde_nade/adversity/vehicles/headon_adversity.py
terasim_nde_nade/adversity/vehicles/lanechange_adversity.py
terasim_nde_nade/adversity/vehicles/lanechangeabort_adversity.py
terasim_nde_nade/adversity/vehicles/leader_adversity.py
terasim_nde_nade/adversity/vehicles/merge_adversity.py
terasim_nde_nade/adversity/vehicles/trafficrule_adversity.py
terasim_nde_nade/adversity/vru/__init__.py
terasim_nde_nade/adversity/vru/jaywalking_adversity.py
terasim_nde_nade/adversity/vru/runningredlight_adversity.py
terasim_nde_nade/adversity/vru/stopcrossing_adversity.py
terasim_nde_nade/envs/__init__.py
terasim_nde_nade/envs/nade.py
terasim_nde_nade/envs/nade_with_av.py
terasim_nde_nade/envs/nde.py
terasim_nde_nade/params.py
terasim_nde_nade/utils/__init__.py
terasim_nde_nade/utils/adversity/__init__.py
terasim_nde_nade/utils/adversity/abstract_adversity.py
terasim_nde_nade/utils/adversity/adversity_builder.py
terasim_nde_nade/utils/adversity/adversity_manager.py
terasim_nde_nade/utils/adversity/follower_adversity.py
terasim_nde_nade/utils/adversity/lane_change_abort_adversity.py
terasim_nde_nade/utils/adversity/lane_change_adversity.py
terasim_nde_nade/utils/adversity/leader_adversity.py
terasim_nde_nade/utils/adversity/merge_adversity.py
terasim_nde_nade/utils/adversity/obs_processing.py
terasim_nde_nade/utils/adversity/traffic_rule_adversity.py
terasim_nde_nade/utils/agents/__init__.py
terasim_nde_nade/utils/agents/base.py
terasim_nde_nade/utils/agents/vehicle.py
terasim_nde_nade/utils/agents/vru.py
terasim_nde_nade/utils/base/__init__.py
terasim_nde_nade/utils/base/nde_command.py
terasim_nde_nade-0.1.2.dist-info/LICENSE
terasim_nde_nade-0.1.2.dist-info/METADATA
terasim_nde_nade-0.1.2.dist-info/WHEEL
terasim_nde_nade-0.1.2.dist-info/RECORD
