Metadata-Version: 2.3
Name: terasim_nde_nade
Version: 0.1.2
Summary: TeraSim NDE NADE package
License: CC BY-NC 4.0
Author: Haowei Sun
Author-email: haoweis@umich.edu
Requires-Python: >=3.10
Classifier: License :: Other/Proprietary License
Classifier: Operating System :: OS Independent
Classifier: Programming Language :: Python :: 3
Classifier: Programming Language :: Python :: 3.10
Classifier: Programming Language :: Python :: 3.11
Classifier: Programming Language :: Python :: 3.12
Classifier: Programming Language :: Python :: 3.13
Requires-Dist: Cython (>=3.0.8)
Requires-Dist: hydra-core (>=1.3.2)
Requires-Dist: loguru (>=0.7.0)
Requires-Dist: omegaconf (>=2.3.0)
Requires-Dist: shapely (>=2.0.3)
Requires-Dist: toml (>=0.10.2)
Project-URL: Repository, https://github.com/michigan-traffic-lab/TeraSim-NDE-ITE
